[
  {
    "id": "655493c288a534ceaab1c2b1",
    "authorName": "Taylor Estrada",
    "blog_title": "Master in javascript es6 platform\r\n",
    "images": "../src/assets/images/profile.png",
    "blogCoverImage": "../src/assets/images/1.jpg",
    "authorImage": "../src/assets/images/boy1.png",
    "readtime": 5,
    "quantity": 0,
    "publishdate": "2023-12-04T06:06:19"
  },
  {
    "id": "655493c2c783c6f373bf91d32",
    "authorName": "Melva Frye",
    "blog_title": "Master in ethical hacking  bootcamp",
    "images": "../src/assets/images/profile.png",
    "blogCoverImage": "../src/assets/images/2.png",
    "authorImage": "../src/assets/images/boy2.png",
    "readtime": 10,
    "quantity": 0,
    "publishdate": "2022-12-04T06:06:19"
  },
  {
    "id": "655493c21ea7de2fd9dadb423",
    "authorName": "Carson Bradshaw",
    "blog_title": "Master in Reactjs 3 month bootcamp",
    "images": "../src/assets/images/profile.png",
    "blogCoverImage": "../src/assets/images/3.png",
    "authorImage": "../src/assets/images/girl1.jpg",
    "readtime": 15,
    "quantity": 0,
    "publishdate": "2020-07-14T11:16:03"
  },
  {
    "id": "655493c26af4da3a2f674b734",
    "authorName": "Glean Maxwell",
    "blog_title": "Use free resources as youtube, coursera, freecodecamp ",
    "images": "../src/assets/images/profile.png",
    "blogCoverImage": "../src/assets/images/4.jpg",
    "authorImage": "../src/assets/images/girl2.jpg",
    "readtime": 20,
    "quantity": 0,
    "publishdate": "2017-12-16T08:59:56"
  }

]